LICENCE
README.md
setup.py
cryptodo/__init__.py
cryptodo.egg-info/PKG-INFO
cryptodo.egg-info/SOURCES.txt
cryptodo.egg-info/dependency_links.txt
cryptodo.egg-info/top_level.txt