Metadata-Version: 2.1
Name: cryptodo
Version: 3.3
Summary: A Python library for text encryption and decryption
Home-page: https://github.com/ishanoshada/cryptodo
Author: k.a.ishan oshada
Author-email: ic31908@gmail.com
License: UNKNOWN
Keywords: text encryption,text decryption,Caesar cipher,substitution cipher,rail fence cipher
Platform: UNKNOWN
Classifier: Development Status :: 1 - Planning
Classifier: Intended Audience :: Developers
Classifier: Programming Language :: Python :: 3
Classifier: Operating System :: OS Independent
Classifier: License :: OSI Approved :: MIT License
Requires-Python: >=3.6
